opentelemetry_python_instrumentation_jobs/__init__.py
opentelemetry_python_instrumentation_jobs/fake_exporters.py
opentelemetry_python_instrumentation_jobs/log_handler.py
opentelemetry_python_instrumentation_jobs/metrics.py
opentelemetry_python_instrumentation_jobs-0.3.2.dist-info/LICENSE
opentelemetry_python_instrumentation_jobs-0.3.2.dist-info/METADATA
opentelemetry_python_instrumentation_jobs-0.3.2.dist-info/WHEEL
opentelemetry_python_instrumentation_jobs-0.3.2.dist-info/RECORD
