Metadata-Version: 2.1
Name: opentelemetry-python-instrumentation-jobs
Version: 0.3.2
Summary: This is a library that allows you to send metrics and logs of scheduled jobs in python to otel-collector.
License: MIT
Author: Vano Atabegashvili
Author-email: vano.atabegashvili@gmail.com
Requires-Python: >=3.9,<4.0
Classifier: License :: OSI Approved :: MIT License
Classifier: Programming Language :: Python :: 3
Classifier: Programming Language :: Python :: 3.9
Classifier: Programming Language :: Python :: 3.10
Classifier: Programming Language :: Python :: 3.11
Classifier: Programming Language :: Python :: 3.12
Classifier: Programming Language :: Python :: 3.13
Requires-Dist: opentelemetry-api (==1.28.1)
Requires-Dist: opentelemetry-exporter-otlp (==1.28.1)
Requires-Dist: opentelemetry-instrumentation-logging (==0.49b1)
Requires-Dist: opentelemetry-sdk (==1.28.1)
Requires-Dist: tqdm (==4.67.0)
